.VERSION
AUTHORS.rst
CONTRIBUTING.rst
HISTORY.rst
LICENSE
MANIFEST.in
Pipfile
Pipfile.lock
README.rst
USAGE.rst
dev-requirements.txt
requirements.txt
setup.cfg
setup.py
docs/Makefile
docs/authors.rst
docs/conf.py
docs/contributing.rst
docs/history.rst
docs/index.rst
docs/installation.rst
docs/readme.rst
docs/usage.rst
taxydromikilib/.VERSION
taxydromikilib/AUTHORS.rst
taxydromikilib/CONTRIBUTING.rst
taxydromikilib/HISTORY.rst
taxydromikilib/LICENSE
taxydromikilib/Pipfile
taxydromikilib/Pipfile.lock
taxydromikilib/README.rst
taxydromikilib/USAGE.rst
taxydromikilib/__init__.py
taxydromikilib/_version.py
taxydromikilib/dev-requirements.txt
taxydromikilib/requirements.txt
taxydromikilib/taxydromikilib.py
taxydromikilib/taxydromikilibexceptions.py
taxydromikilib.egg-info/PKG-INFO
taxydromikilib.egg-info/SOURCES.txt
taxydromikilib.egg-info/dependency_links.txt
taxydromikilib.egg-info/not-zip-safe
taxydromikilib.egg-info/requires.txt
taxydromikilib.egg-info/top_level.txt