Metadata-Version: 2.1
Name: taxydromikilib
Version: 1.0.1
Summary: A small library to search taxydromiki for parsels and their status.
Home-page: https://github.com/costastf/taxydromikilib
Author: Costas Tyfoxylos
Author-email: costas.tyf@gmail.com
License: MIT
Keywords: taxydromikilib
Platform: UNKNOWN
Classifier: Development Status :: 4 - Beta
Classifier: Intended Audience :: Developers
Classifier: License :: OSI Approved :: MIT License
Classifier: Natural Language :: English
Classifier: Programming Language :: Python :: 3.7
License-File: LICENSE
License-File: AUTHORS.rst
